{"is_source_file": true, "format": "bash", "description": "This script automates the backup process for various databases (SQLite, PostgreSQL, MySQL, MongoDB). It detects which database is running and performs the backup accordingly, saving the backup files and providing status messages.", "external_files": ["/usr/lib/postgresql/", "/var/run/mysqld/mysqld.sock"], "external_methods": ["ls", "sudo", "pg_isready", "mysqladmin", "mysql", "mysqldump", "mongosh", "mongodump"], "published": [], "classes": [], "methods": [], "calls": ["ls", "echo", "cp", "exit", "sudo -u postgres pg_isready", "sudo mysqladmin ping", "mysqladmin ping", "mysql -h localhost -P ${DB_PORT} -u ${DB_USER} -p${DB_PASSWORD}", "mysqldump", "sudo mysql --socket=/var/run/mysqld/mysqld.sock", "sudo mysqldump", "mongosh --port ${DB_PORT} --eval \"db.adminCommand('ping')\"", "mongodump --port ${DB_PORT} --db ${DB_NAME}"], "search-terms": ["database backup bash script", "SQLite PostgreSQL MySQL MongoDB backup", "detect running database", "automated database backup", "multi-database support", "database detection script"], "state": 2, "file_id": 2, "knowledge_revision": 12, "git_revision": "18aff44f90f1cb670fbe3c888f0178054c1cfe29", "hash": "7af9aa35fa4940f934d83f6e2621b732", "format-version": 4, "code-base-name": "database", "filename": "database/backup_db.sh", "revision_history": [{"12": "18aff44f90f1cb670fbe3c888f0178054c1cfe29"}]}